tpds/__init__.py
tpds/device_manifest/__init__.py
tpds/device_manifest/__main__.py
tpds/device_manifest/generate_manifest_data.py
tpds/device_manifest/helper.py
tpds/device_manifest/info_schema.yaml
tpds/device_manifest/manifest_cli.py
tpds/device_manifest/ca_element/__init__.py
tpds/device_manifest/ca_element/ca_element.py
tpds/device_manifest/ca_element/info.yaml
tpds/device_manifest/connect/__init__.py
tpds/device_manifest/connect/connect.py
tpds/device_manifest/manifest/__init__.py
tpds/device_manifest/manifest/manifest.py
tpds_device_manifest-1.0.1.dist-info/licenses/LICENSE
tpds_device_manifest-1.0.1.dist-info/METADATA
tpds_device_manifest-1.0.1.dist-info/WHEEL
tpds_device_manifest-1.0.1.dist-info/entry_points.txt
tpds_device_manifest-1.0.1.dist-info/top_level.txt
tpds_device_manifest-1.0.1.dist-info/RECORD
