Metadata-Version: 2.4
Name: tpds-device-manifest
Version: 1.0.1
Summary: Microchip Secure Devices Manifest Generation and Decoding Support
Maintainer-email: Microchip Technology <SPG.Tools@microchip.com>
License: (c) 2018 to present - Copyright Microchip Technology Inc. and its subsidiaries.
Classifier: License :: Other/Proprietary License
Classifier: Development Status :: 4 - Beta
Classifier: Programming Language :: Python :: 3
Classifier: Operating System :: OS Independent
Requires-Python: >=3.10
License-File: LICENSE
Requires-Dist: python_jose
Requires-Dist: cryptography~=35.0.0
Requires-Dist: tpds-certificate-tools
Requires-Dist: cryptoauthlib>=20241015
Requires-Dist: PyYAML
Requires-Dist: jsonschema
Provides-Extra: dev
Requires-Dist: flake8; extra == "dev"
Requires-Dist: black; extra == "dev"
Requires-Dist: isort; extra == "dev"
Requires-Dist: mypy; extra == "dev"
Provides-Extra: test
Requires-Dist: pytest-cov; extra == "test"
Requires-Dist: pytest-mock; extra == "test"
Requires-Dist: pytest-integration; extra == "test"
Dynamic: license-file
